pystratum_common/__init__.py
pystratum_common/backend/CommonConstantWorker.py
pystratum_common/backend/CommonRoutineLoaderWorker.py
pystratum_common/backend/CommonRoutineWrapperGeneratorWorker.py
pystratum_common/backend/__init__.py
pystratum_common/constant/ConstantClass.py
pystratum_common/constant/__init__.py
pystratum_common/exception/LoaderException.py
pystratum_common/exception/__init__.py
pystratum_common/helper/CommonMetadataDataLayer.py
pystratum_common/helper/Util.py
pystratum_common/helper/__init__.py
pystratum_common/loader/CommonRoutineLoader.py
pystratum_common/loader/__init__.py
pystratum_common/loader/helper/CommonDataTypeHelper.py
pystratum_common/loader/helper/DocBlockHelper.py
pystratum_common/loader/helper/DocBlockReflection.py
pystratum_common/loader/helper/LoaderContext.py
pystratum_common/loader/helper/PlaceholderHelper.py
pystratum_common/loader/helper/StoredRoutineHelper.py
pystratum_common/loader/helper/TypeHintHelper.py
pystratum_common/loader/helper/__init__.py
pystratum_common/wrapper/CommonBulkWrapper.py
pystratum_common/wrapper/CommonFunctionsWrapper.py
pystratum_common/wrapper/CommonInsertManyWrapper.py
pystratum_common/wrapper/CommonLogWrapper.py
pystratum_common/wrapper/CommonMultiWrapper.py
pystratum_common/wrapper/CommonNoneWrapper.py
pystratum_common/wrapper/CommonRow0Wrapper.py
pystratum_common/wrapper/CommonRow1Wrapper.py
pystratum_common/wrapper/CommonRowsWithIndexWrapper.py
pystratum_common/wrapper/CommonRowsWithKeyWrapper.py
pystratum_common/wrapper/CommonRowsWrapper.py
pystratum_common/wrapper/CommonSingleton0Wrapper.py
pystratum_common/wrapper/CommonSingleton1Wrapper.py
pystratum_common/wrapper/CommonTableWrapper.py
pystratum_common/wrapper/CommonWrapper.py
pystratum_common/wrapper/__init__.py
pystratum_common/wrapper/helper/PythonCodeStore.py
pystratum_common/wrapper/helper/WrapperContext.py
pystratum_common/wrapper/helper/__init__.py
pystratum_common-3.1.1.dist-info/LICENSE.md
pystratum_common-3.1.1.dist-info/METADATA
pystratum_common-3.1.1.dist-info/WHEEL
pystratum_common-3.1.1.dist-info/RECORD
