Metadata-Version: 2.1
Name: PyStratum-Common
Version: 3.1.1
Summary: PyStratum Common: Common parts shared between commons for database systems
Home-page: https://github.com/DatabaseStratum/py-stratum-common
License: MIT
Keywords: PyStratum,Common
Author: Set Based IT Consultancy
Author-email: info@setbased.nl
Requires-Python: >=3.12.0,<4.0.0
Classifier: Development Status :: 5 - Production/Stable
Classifier: Intended Audience :: Developers
Classifier: License :: OSI Approved :: MIT License
Classifier: Programming Language :: Python :: 3
Classifier: Programming Language :: Python :: 3.12
Classifier: Topic :: Software Development :: Build Tools
Classifier: Topic :: Software Development :: Code Generators
Classifier: Topic :: System :: Installation/Setup
Requires-Dist: pystratum-backend (>=2.0.4,<3.0.0)
Project-URL: Documentation, https://stratum.readthedocs.io/
Project-URL: Repository, https://github.com/DatabaseStratum/py-stratum-common
